{
  "sections": {
    "main": {
      "type": "ma-policy",
      "settings": {
        "icon": "refund",
        "body": "<p>Due to hygiene and safety standards, fragrances cannot be returned once opened or used. However, we offer 7 days return policy incase of product received in damage condition or in situation received wrong product, we will support you promptly in the case of errors or transit damage.</p><p><strong>A. Replacement — Eligible Situations</strong></p><p>A replacement will be provided when:</p><ul><li>A wrong product has been delivered</li><li>The product was received damaged in transit</li><li>A confirmed manufacturing defect is present</li></ul><p><strong>Requirements for Replacement:</strong><br>You must provide the following within 24 hours of delivery:</p><ul><li>An unboxing video (recorded from start to end, without interruption)</li><li>Clear photos of the product and packaging showing the damage or error</li></ul><p>Upon verification, we will dispatch a replacement at no additional charge.</p><p><strong>B. Refunds — Eligible Situations</strong></p><p>A refund will be issued only when:</p><ul><li>The product cannot be replaced because it is out of stock</li><li>A confirmed cancellation request was made before dispatch — in this case, the refund will be processed after deducting payment gateway charges as applicable (typically 1.5%–3.5% of the order value, depending on your bank or payment method)</li></ul><p><strong>Refund Timeline:</strong><br>Refunds are processed within 3–7 working days, depending on your payment method and bank's processing time.</p><p><strong>C. No Returns for Opened or Used Products</strong></p><p>Opened, used, or unhygienic items are not accepted for return under any circumstances. Please inspect your parcel carefully at the time of delivery. If you notice any damage, retain the original packaging and record an unboxing video immediately.</p><p><strong>D. Cancellation Policy</strong></p><ul><li><strong>Before dispatch:</strong> You may cancel your order before it is dispatched. A refund will be issued after deducting payment gateway charges levied on the transaction.</li><li><strong>After dispatch:</strong> Cancellations are not accepted once the order has been dispatched.</li><li><strong>How to cancel:</strong> Send your cancellation request via WhatsApp or Email with your Order ID as soon as possible.</li><li><strong>No COD:</strong> As Maison Amiir does not offer Cash on Delivery, COD cancellations are not applicable.</li></ul><p><strong>E. Contact for Claims</strong></p><p>Reach us via WhatsApp or Email at <a href=\"mailto:info@maisonamiir.com\">info@maisonamiir.com</a> within 24 hours of delivery for any replacement or refund requests.</p>"
      }
    }
  },
  "order": ["main"]
}
